asgi_aiogram/__init__.py
asgi_aiogram/aliases.py
asgi_aiogram/asgi.py
asgi_aiogram/exceptions.py
asgi_aiogram/http_request.py
asgi_aiogram/http_responses.py
asgi_aiogram/main.py
asgi_aiogram/path_normalization.py
asgi_aiogram/responses.py
asgi_aiogram/strategy/__init__.py
asgi_aiogram/strategy/base.py
asgi_aiogram/strategy/http.py
asgi_aiogram/strategy/single.py
asgi_aiogram/strategy/token_based.py
asgi_aiogram/types.py
asgi_aiogram-0.3.1.dist-info/METADATA
asgi_aiogram-0.3.1.dist-info/WHEEL
asgi_aiogram-0.3.1.dist-info/RECORD
