Metadata-Version: 2.1
Name: asgi_aiogram
Version: 0.3.1
Summary: fast ASGI wraper for aiogram
License: MIT
Author: RootShinobi
Author-email: 111008396+RootShinobi@users.noreply.github.com
Requires-Python: >=3.9,<4.0
Classifier: License :: OSI Approved :: MIT License
Classifier: Programming Language :: Python :: 3
Classifier: Programming Language :: Python :: 3.9
Classifier: Programming Language :: Python :: 3.10
Classifier: Programming Language :: Python :: 3.11
Classifier: Programming Language :: Python :: 3.12
Classifier: Programming Language :: Python :: 3.13
Requires-Dist: aiogram (>=3.9,<4.0)
